trackers/__init__.py
trackers/log.py
trackers/core/__init__.py
trackers/core/base.py
trackers/core/deepsort/__init__.py
trackers/core/deepsort/feature_extractor.py
trackers/core/deepsort/kalman_box_tracker.py
trackers/core/deepsort/tracker.py
trackers/core/sort/__init__.py
trackers/core/sort/kalman_box_tracker.py
trackers/core/sort/tracker.py
trackers/utils/__init__.py
trackers/utils/sort_utils.py
trackers/utils/torch_utils.py
trackers-2.0.1.dist-info/METADATA
trackers-2.0.1.dist-info/WHEEL
trackers-2.0.1.dist-info/licenses/LICENSE
trackers-2.0.1.dist-info/RECORD
