Metadata-Version: 2.4
Name: trackers
Version: 2.0.1
Summary: A unified library for object tracking featuring clean room re-implementations of leading multi-object tracking algorithms
Author-email: Piotr Skalski <piotr.skalski92@gmail.com>, Soumik Rakshit <soumik@roboflow.com>
License: Apache License 2.0
License-File: LICENSE
Keywords: AI,DETR,DL,ML,Roboflow,YOLO,deep-learning,deepsort,machine-learning,mot,sort,tracking,vision
Classifier: Development Status :: 4 - Beta
Classifier: Intended Audience :: Developers
Classifier: Intended Audience :: Education
Classifier: Intended Audience :: Science/Research
Classifier: License :: OSI Approved :: Apache Software License
Classifier: Operating System :: MacOS
Classifier: Operating System :: Microsoft :: Windows
Classifier: Operating System :: POSIX
Classifier: Operating System :: Unix
Classifier: Programming Language :: Python :: 3
Classifier: Programming Language :: Python :: 3 :: Only
Classifier: Programming Language :: Python :: 3.9
Classifier: Programming Language :: Python :: 3.10
Classifier: Programming Language :: Python :: 3.11
Classifier: Programming Language :: Python :: 3.12
Classifier: Programming Language :: Python :: 3.13
Classifier: Topic :: Scientific/Engineering
Classifier: Topic :: Scientific/Engineering :: Artificial Intelligence
Classifier: Topic :: Software Development
Classifier: Typing :: Typed
Requires-Python: >=3.9
Requires-Dist: firerequests>=0.1.2
Requires-Dist: numpy>=2.0.2
Requires-Dist: supervision>=0.26.0rc7
Requires-Dist: validators>=0.34.0
Provides-Extra: cpu
Requires-Dist: torch>=2.6.0; extra == 'cpu'
Requires-Dist: torchvision>=0.21.0; extra == 'cpu'
Provides-Extra: cu118
Requires-Dist: torch>=2.6.0; extra == 'cu118'
Requires-Dist: torchvision>=0.21.0; extra == 'cu118'
Provides-Extra: cu124
Requires-Dist: torch>=2.6.0; extra == 'cu124'
Requires-Dist: torchvision>=0.21.0; extra == 'cu124'
Provides-Extra: cu126
Requires-Dist: torch>=2.6.0; extra == 'cu126'
Requires-Dist: torchvision>=0.21.0; extra == 'cu126'
Provides-Extra: deepsort
Requires-Dist: scipy>=1.13.1; extra == 'deepsort'
Requires-Dist: timm>=1.0.15; extra == 'deepsort'
Provides-Extra: rocm61
Requires-Dist: pytorch-triton-rocm>=2.0.0; extra == 'rocm61'
Requires-Dist: torch>=2.6.0; extra == 'rocm61'
Requires-Dist: torchvision>=0.21.0; extra == 'rocm61'
Provides-Extra: rocm624
Requires-Dist: pytorch-triton-rocm>=2.0.0; extra == 'rocm624'
Requires-Dist: torch>=2.6.0; extra == 'rocm624'
Requires-Dist: torchvision>=0.21.0; extra == 'rocm624'
